terasim/__init__.py
terasim/agent/__init__.py
terasim/agent/agent.py
terasim/agent/agent_controller.py
terasim/agent/agent_decision_model.py
terasim/agent/agent_sensor.py
terasim/configs.py
terasim/envs/__init__.py
terasim/envs/base.py
terasim/envs/base_complete.py
terasim/envs/template.py
terasim/envs/template_complete.py
terasim/envs/template_traffic_light.py
terasim/logger/__init__.py
terasim/logger/infoextractor.py
terasim/measure/__init__.py
terasim/measure/measure.py
terasim/network/__init__.py
terasim/network/trafficnet.py
terasim/overlay.py
terasim/params.py
terasim/pipeline.py
terasim/simulator.py
terasim/traffic_light/__init__.py
terasim/traffic_light/controllers/__init__.py
terasim/traffic_light/controllers/state_controller.py
terasim/traffic_light/decision_models/__init__.py
terasim/traffic_light/decision_models/dummy_state_decision_model.py
terasim/traffic_light/factories/__init__.py
terasim/traffic_light/factories/traffic_light_factory.py
terasim/traffic_light/sensors/ego_state_sensor.py
terasim/traffic_light/traffic_light.py
terasim/utils.py
terasim/vehicle/__init__.py
terasim/vehicle/controllers/__init__.py
terasim/vehicle/controllers/high_efficiency_controller.py
terasim/vehicle/controllers/sumo_move_controller.py
terasim/vehicle/decision_models/__init__.py
terasim/vehicle/decision_models/dummy_setsumo_transform_decision_model.py
terasim/vehicle/decision_models/highway_base_decision_model.py
terasim/vehicle/decision_models/idm_model.py
terasim/vehicle/decision_models/sumo_model.py
terasim/vehicle/factories/__init__.py
terasim/vehicle/factories/vehicle_factory.py
terasim/vehicle/sensors/__init__.py
terasim/vehicle/sensors/ego.py
terasim/vehicle/sensors/local.py
terasim/vehicle/vehicle.py
terasim/vulnerable_road_user/controllers/sumo_move_controller.py
terasim/vulnerable_road_user/decision_models/sumo_model.py
terasim/vulnerable_road_user/factories/vulnerable_road_user_factory.py
terasim/vulnerable_road_user/sensors/ego.py
terasim-0.1.0.dist-info/LICENSE
terasim-0.1.0.dist-info/METADATA
terasim-0.1.0.dist-info/WHEEL
terasim-0.1.0.dist-info/RECORD
