Metadata-Version: 2.1
Name: terasim
Version: 0.1.0
Summary: Generative AV testing environment for unknown unsafe events discovery
License: Apache-2.0
Author: Haowei Sun
Author-email: haoweis@umich.edu
Requires-Python: >=3.9,<3.13
Classifier: License :: OSI Approved :: Apache Software License
Classifier: Programming Language :: Python :: 3
Classifier: Programming Language :: Python :: 3.9
Classifier: Programming Language :: Python :: 3.10
Classifier: Programming Language :: Python :: 3.11
Classifier: Programming Language :: Python :: 3.12
Requires-Dist: addict (>=2.4.0,<3.0.0)
Requires-Dist: attrs (>=23.2.0,<24.0.0)
Requires-Dist: bidict (>=0.23.1,<0.24.0)
Requires-Dist: eclipse-sumo (>=1.19.0,<1.20.0)
Requires-Dist: libsumo (>=1.19.0,<1.20.0)
Requires-Dist: loguru (>=0.7.2,<0.8.0)
Requires-Dist: lxml (>=5.1.0,<6.0.0)
Requires-Dist: numpy (>=1.26.4,<2.0.0)
Requires-Dist: pydantic (>=2.6.3,<3.0.0)
Requires-Dist: pyproj (>=3.6.1,<4.0.0)
Requires-Dist: redis (>=5.0.2,<6.0.0)
Requires-Dist: rtree (>=1.0.1,<2.0.0)
Requires-Dist: scipy (>=1.11.4,<2.0.0)
Requires-Dist: sumolib (>=1.19.0,<1.20.0)
Requires-Dist: traci (>=1.19.0,<1.20.0)
